edge2client/__init__.py
edge2client/constants.py
edge2client/edge2client.py
edge2client/edge_common.py
edge2client/utils_common.py
edge2client/version.py
edge2client/utils/batch_release.py
edge2client/utils/copy_app.py
edge2client/utils/create_app.py
edge2client/utils/create_apps.py
edge2client/utils/delete_all_apps.py
edge2client/utils/export_apps.py
edge2client/utils/get_app_id_by_global_rule.py
edge2client/utils/global_ini.py
edge2client/utils/ngx_emer_conf.py
edge2client/utils/py_client.py
edge2client/utils/query_rule_id.py
edge2client/utils/release_app.py
edge2client/utils/remove_useless_conf.py
edge2client/utils/sync_eureka.py
edge2client/utils/update_dns.py
edge2client/utils/update_proxy_timeout.py
edge2client/utils/update_src_ip.py
edge2client/utils/update_upstream_group_weight.py
edge2client/utils/update_upstream_weight.py
edge2client/utils/utils_common.py
edge2yaml/basic_auth_groups.py
edge2yaml/edge2yaml.py
edge2yaml/edge_email.py
edge2yaml/edgelang_rules.py
edge2yaml/global_basic_auth_groups.py
edge2yaml/global_configs.py
edge2yaml/global_custom_actions.py
edge2yaml/global_ip_lists.py
edge2yaml/global_k8s_upstreams.py
edge2yaml/global_lua_modules.py
edge2yaml/global_page_templates.py
edge2yaml/global_static_files.py
edge2yaml/global_upstreams.py
edge2yaml/global_variables.py
edge2yaml/http_app.py
edge2yaml/ip_lists.py
edge2yaml/k8s.py
edge2yaml/k8s_upstreams.py
edge2yaml/names.py
edge2yaml/page_rules.py
edge2yaml/read_config.py
edge2yaml/test.py
edge2yaml/upstreams.py
edge2yaml/user_variables.py
edge2yaml/users.py
edge2yaml/utils.py
edge2yaml/waf_whitelist.py
openresty_edge_sdk-1.2.79.data/scripts/edge-config
openresty_edge_sdk-1.2.79.data/scripts/edge2yaml
openresty_edge_sdk-1.2.79.dist-info/licenses/LICENSE
openresty_edge_sdk-1.2.79.dist-info/METADATA
openresty_edge_sdk-1.2.79.dist-info/WHEEL
openresty_edge_sdk-1.2.79.dist-info/top_level.txt
openresty_edge_sdk-1.2.79.dist-info/RECORD
