Metadata-Version: 2.4
Name: openresty-edge-sdk
Version: 1.2.79
Summary: OpenResty Edge Python SDK
Home-page: https://www.openresty.com
Author: OpenResty Inc.
Author-email: support@openresty.com
Keywords: openresty-edge-sdk,edge2client,python,sdk
Platform: Platform Independent
Classifier: Development Status :: 5 - Production/Stable
Classifier: Intended Audience :: Developers
Classifier: Operating System :: OS Independent
Classifier: Programming Language :: Python
Classifier: Programming Language :: Python :: 3
Classifier: Programming Language :: Python :: 3.6
Classifier: Programming Language :: Python :: 3.7
Classifier: Programming Language :: Python :: 3.8
Classifier: Programming Language :: Python :: 3.9
License-File: LICENSE
Requires-Dist: requests
Requires-Dist: urllib3
Requires-Dist: pyOpenSSL
Requires-Dist: ruamel.yaml
Requires-Dist: jinja2
Dynamic: author
Dynamic: author-email
Dynamic: classifier
Dynamic: description
Dynamic: description-content-type
Dynamic: home-page
Dynamic: keywords
Dynamic: license-file
Dynamic: platform
Dynamic: requires-dist
Dynamic: summary
